loggingx/__init__.py
loggingx/config.py
loggingx/context.py
loggingx/formatter.py
loggingx/handlers.py
loggingx/json.py
loggingx/json_test.py
loggingx/py.typed
loggingx_py-0.12.0.dist-info/LICENSE
loggingx_py-0.12.0.dist-info/METADATA
loggingx_py-0.12.0.dist-info/WHEEL
loggingx_py-0.12.0.dist-info/top_level.txt
loggingx_py-0.12.0.dist-info/RECORD
