Metadata-Version: 2.1
Name: loggingx-py
Version: 0.12.0
Summary: Drop-in replacement for Python's built-in `logging` module
Author-email: Hyeonki Hong <hhk7734@gmail.com>
License: MIT License
Project-URL: repository, https://github.com/hhk7734/loggingx.py
Keywords: logging,contextual-logging,structured-logging
Classifier: Programming Language :: Python :: 3
Classifier: Intended Audience :: Developers
Requires-Python: <4.0,>=3.8
License-File: LICENSE
